geodome/__init__.py
geodome/geodesic_dome.py
geodome/neighbourhood_search.py
geodome/tessellation.py
geodome/test.py
tests/__init__.py
tests/broken_test_middle_points.py
tests/broken_test_selective_tessellation.py
tests/broken_test_tessellation.py
tests/test_class_wrapper.py
tests/test_dome_creation.py
tests/test_is_zero.py
tests/test_neighbourhood_search.py
tests/test_normalise_length.py
geodome-1.0.0.dist-info/LICENSE
geodome-1.0.0.dist-info/METADATA
geodome-1.0.0.dist-info/WHEEL
geodome-1.0.0.dist-info/top_level.txt
geodome-1.0.0.dist-info/RECORD
