Metadata-Version: 2.1
Name: geodome
Version: 1.0.0
Summary: A performant python Geodesic Dome library developed for the University of Sydney capstone unit
Home-page: https://bitbucket.org/soft3888_m17_01_group4/soft3888_m17_01_group4/src/master/
Author: Kevin Cai, Manan Choksi, Samuel Chen, Lewis Krishnamurti, Jacob Pratley, James Asher
License: UNKNOWN
Project-URL: Bug Tracker, https://soft3888-m17-01-group4.atlassian.net/jira/software/projects/SM0G/boards/1
Platform: UNKNOWN
Classifier: Programming Language :: Python :: 3
Classifier: License :: OSI Approved :: MIT License
Classifier: Operating System :: OS Independent
Requires-Python: >=3.6
License-File: LICENSE
